iqm/pypitest/__init__.py
iqm_pypitest-0.4.dist-info/LICENSE.txt
iqm_pypitest-0.4.dist-info/METADATA
iqm_pypitest-0.4.dist-info/WHEEL
iqm_pypitest-0.4.dist-info/top_level.txt
iqm_pypitest-0.4.dist-info/RECORD
