Metadata-Version: 2.1
Name: iqm-pypitest
Version: 0.4
Summary: A dummy package for testing IQM's Python packaging
Author-email: IQM Finland Oy <developers@meetiqm.com>
License: Copyright (c) 2021-2024 IQM Finland Oy.
Project-URL: Homepage, https://github.com/iqm-finland/iqm-pypitest
Project-URL: Documentation, https://github.com/iqm-finland/iqm-pypitest
Classifier: Development Status :: 4 - Beta
Classifier: Programming Language :: Python :: 3 :: Only
Classifier: Topic :: Scientific/Engineering :: Physics
Classifier: Intended Audience :: Science/Research
Classifier: License :: OSI Approved :: Apache Software License
Requires-Python: <3.12,>=3.11
License-File: LICENSE.txt
Requires-Dist: pydantic<3.0,>=2.4.2
Provides-Extra: dev
Requires-Dist: tox==4.11.3; extra == "dev"
Requires-Dist: tox-extras==0.0.2; extra == "dev"
